setup.py
PIL_ext/PIL_ext.py
PIL_ext/__init__.py
PIL_ext.egg-info/PKG-INFO
PIL_ext.egg-info/SOURCES.txt
PIL_ext.egg-info/dependency_links.txt
PIL_ext.egg-info/requires.txt
PIL_ext.egg-info/top_level.txt