Metadata-Version: 1.2
Name: PIL-ext
Version: 0.1
Summary: Some extend methods for Pillow(PIL)
Home-page: https://github.com/Danny-Yxzl/PIL_ext
Author: Yixiangzhilv
Author-email: mail@yixiangzhilv.com
License: UNKNOWN
Project-URL: Bug Reports, https://github.com/Danny-Yxzl/PIL_ext/issues
Project-URL: Say Thanks!, https://www.yixiangzhilv.com/
Project-URL: Source, https://github.com/Danny-Yxzl/PIL_ext
Keywords: image PIL
Platform: UNKNOWN
Classifier: Intended Audience :: Developers
Classifier: License :: OSI Approved :: MIT License
Classifier: Programming Language :: Python :: 3
Classifier: Programming Language :: Python :: 3.6
Classifier: Programming Language :: Python :: 3.7
Classifier: Programming Language :: Python :: 3.8
Classifier: Programming Language :: Python :: 3.9
Classifier: Programming Language :: Python :: 3.10
